easycloudapi/__init__.py
easycloudapi/gcp/__init__.py
easycloudapi/gcp/bigquery/__init__.py
easycloudapi/gcp/bigquery/bigquery_schema.py
easycloudapi/generic/__init__.py
easycloudapi/generic/datetime/__init__.py
easycloudapi/generic/datetime/generate_date_dimention.py
easycloudapi-0.0.3.dist-info/LICENSE
easycloudapi-0.0.3.dist-info/METADATA
easycloudapi-0.0.3.dist-info/WHEEL
easycloudapi-0.0.3.dist-info/top_level.txt
easycloudapi-0.0.3.dist-info/RECORD
