Metadata-Version: 2.1
Name: easycloudapi
Version: 0.0.3
Summary: Providing utility functions to help other python developers
Home-page: https://github.com/easycloudapi/python_utility
Author: Indranil Pal
Author-email: info.easycloudapi@gmail.com
Project-URL: Bug Tracker, https://github.com/easycloudapi/python_utility/issues
Project-URL: repository, https://github.com/easycloudapi/python_utility
Keywords: utility,gcp
Classifier: Programming Language :: Python :: 3
Classifier: License :: OSI Approved :: MIT License
Classifier: Operating System :: OS Independent
Requires-Python: >=3.8
License-File: LICENSE
Requires-Dist: pandas (==2.0.2)
Requires-Dist: numpy (==1.25.2)
